ics_caldav_sync.py
ics_caldav_sync-1.1.dist-info/licenses/LICENSE
ics_caldav_sync-1.1.dist-info/METADATA
ics_caldav_sync-1.1.dist-info/WHEEL
ics_caldav_sync-1.1.dist-info/entry_points.txt
ics_caldav_sync-1.1.dist-info/top_level.txt
ics_caldav_sync-1.1.dist-info/RECORD
