Metadata-Version: 2.4
Name: ics_caldav_sync
Version: 1.1
Summary: ICS to CalDAV synchronisation.
Author-email: Przemysław Buczkowski <prem@prem.moe>
License-Expression: MIT
Project-URL: Repository, https://github.com/przemub/ics_caldav_sync
Keywords: ics,caldav,sync,synchronization,calendar,icalendar
Classifier: Development Status :: 5 - Production/Stable
Classifier: Environment :: Console
Classifier: Intended Audience :: End Users/Desktop
Classifier: Programming Language :: Python :: 3 :: Only
Classifier: Programming Language :: Python :: 3.9
Classifier: Programming Language :: Python :: 3.10
Classifier: Programming Language :: Python :: 3.11
Classifier: Programming Language :: Python :: 3.12
Classifier: Programming Language :: Python :: 3.13
Classifier: Topic :: Office/Business :: Scheduling
Classifier: Topic :: Internet
Requires-Python: >=3.9
License-File: LICENSE
Requires-Dist: arrow==1.4.0
Requires-Dist: caldav==2.0.1
Requires-Dist: certifi==2025.11.12
Requires-Dist: charset-normalizer==3.4.4
Requires-Dist: click==8.3.1
Requires-Dist: icalendar==6.3.2
Requires-Dist: idna==3.11
Requires-Dist: lxml==6.0.2
Requires-Dist: python-dateutil==2.9.0.post0
Requires-Dist: pytz==2025.2
Requires-Dist: recurring-ical-events==3.8.0
Requires-Dist: requests==2.32.5
Requires-Dist: six==1.17.0
Requires-Dist: tzdata==2025.2
Requires-Dist: urllib3==2.5.0
Requires-Dist: vobject==0.9.9
Requires-Dist: x-wr-timezone==2.0.1
Provides-Extra: dev
Requires-Dist: black==25.11.0; extra == "dev"
Requires-Dist: build==1.3.0; extra == "dev"
Requires-Dist: licensecheck==2025.1.0; extra == "dev"
Requires-Dist: types-python-dateutil==2.9.0.20251115; extra == "dev"
Requires-Dist: twine==6.2.0; extra == "dev"
Requires-Dist: vermin==1.8.0; extra == "dev"
Dynamic: license-file
